pipette/__init__.py
pipette/funcs.py
pipette/pipette.py
pipette/curry/__init__.py
pipette/curry/curry.py
pipette/monad/__init__.py
pipette/monad/either.py
pipette/monad/maybe.py
pipette/monad/monad.py
pipette_fp-1.0.0.dist-info/licenses/LICENSE.md
pipette_fp-1.0.0.dist-info/METADATA
pipette_fp-1.0.0.dist-info/WHEEL
pipette_fp-1.0.0.dist-info/top_level.txt
pipette_fp-1.0.0.dist-info/RECORD
