Metadata-Version: 2.4
Name: pipette-fp
Version: 1.0.0
Summary: Functional programming for Python
Requires-Python: >=3.11
License-File: LICENSE.md
Requires-Dist: typing-extensions>=4.14.1
Dynamic: license-file
